syllogistic/__init__.py
syllogistic/__main__.py
syllogistic/main.py
syllogistic/processor.py
syllogistic/watcher.py
syllogistic-0.1.1.dist-info/LICENSE
syllogistic-0.1.1.dist-info/METADATA
syllogistic-0.1.1.dist-info/WHEEL
syllogistic-0.1.1.dist-info/entry_points.txt
syllogistic-0.1.1.dist-info/top_level.txt
syllogistic-0.1.1.dist-info/RECORD
