Metadata-Version: 2.1
Name: syllogistic
Version: 0.1.1
Summary: A simple Lua build system for the TIC-80.
Author-email: Alastair McBain <mcbain.asm+syllogistic@gmail.com>
License: Copyright 2024, Alastair McBain
Project-URL: Homepage, https://bitbucket.org/AMcBain/syllogistic
Project-URL: Documentation, https://bitbucket.org/AMcBain/syllogistic/src/main/docs.md
Project-URL: Release Notes, https://bitbucket.org/AMcBain/syllogistic/src/main/release-notes.md
Project-URL: Issues, https://bitbucket.org/AMcBain/syllogistic/issues
Keywords: TIC-80,Fantasy Console,Build,Build System,LUA
Classifier: Environment :: Console
Classifier: License :: OSI Approved
Classifier: Development Status :: 4 - Beta
Requires-Python: >=3.11
License-File: LICENSE
Requires-Dist: pakettic ~=1.3.1
Requires-Dist: watchdog ~=2.1.5
Provides-Extra: dev
Requires-Dist: pytest ~=8.1.1 ; extra == 'dev'
